yade/__init__.py
yade-0.1.3.dist-info/LICENSE
yade-0.1.3.dist-info/WHEEL
yade-0.1.3.dist-info/METADATA
yade-0.1.3.dist-info/RECORD
