Metadata-Version: 2.1
Name: yade
Version: 0.1.3
Summary: Yet another Django env
Keywords: django,environment,settings
Author-email: djbios <dorandval@gmail.com>
Classifier: License :: OSI Approved :: MIT License
Project-URL: Home, https://github.com/djbios/yade
